{
  "Routes": [
    {
      "DownstreamPathTemplate": "/Code/Python",
      "DownstreamScheme": "http",
      "DownstreamHostAndPorts": [
        {
          "Host": "localhost",
          "Port": 5011
        }
      ],
      "UpstreamPathTemplate": "/Code/Python",
      "UpstreamHttpMethod": [ "POST" ]
    },
    {
      "DownstreamPathTemplate": "/Code/Python/get",
      "DownstreamScheme": "http",
      "DownstreamHostAndPorts": [
        {
          "Host": "localhost",
          "Port": 5011
        }
      ],
      "UpstreamPathTemplate": "/Code/Python/get",
      "UpstreamHttpMethod": [ "GET" ]
    },
    {
      "DownstreamPathTemplate": "/Code/JavaScript",
      "DownstreamScheme": "http",
      "DownstreamHostAndPorts": [
        {
          "Host": "localhost",
          "Port": 5247
        }
      ],
      "UpstreamPathTemplate": "/Code/JavaScript",
      "UpstreamHttpMethod": [ "POST" ]
    },
    {
      "DownstreamPathTemplate": "/Code/JavaScript/get",
      "DownstreamScheme": "http",
      "DownstreamHostAndPorts": [
        {
          "Host": "localhost",
          "Port": 5247
        }
      ],
      "UpstreamPathTemplate": "/Code/JavaScript/get",
      "UpstreamHttpMethod": [ "GET" ]
    }
  ]
}